main.py
skippers.xml
symbols.xml
_locales/en_US/configuration.json
_locales/pt_BR/configuration.json
hatemile/__init__.py
hatemile/accessibleassociation.py
hatemile/accessiblecss.py
hatemile/accessibledisplay.py
hatemile/accessibleevent.py
hatemile/accessibleform.py
hatemile/accessiblenavigation.py
hatemile/helper.py
hatemile/implementation/__init__.py
hatemile/implementation/assoc.py
hatemile/implementation/css.py
hatemile/implementation/display.py
hatemile/implementation/event.py
hatemile/implementation/form.py
hatemile/implementation/navig.py
hatemile/util/__init__.py
hatemile/util/commonfunctions.py
hatemile/util/configure.py
hatemile/util/idgenerator.py
hatemile/util/css/__init__.py
hatemile/util/css/stylesheetdeclaration.py
hatemile/util/css/stylesheetparser.py
hatemile/util/css/stylesheetrule.py
hatemile/util/css/tinycss/__init__.py
hatemile/util/css/tinycss/tinycssdeclaration.py
hatemile/util/css/tinycss/tinycssparser.py
hatemile/util/css/tinycss/tinycssrule.py
hatemile/util/html/__init__.py
hatemile/util/html/htmldomelement.py
hatemile/util/html/htmldomnode.py
hatemile/util/html/htmldomparser.py
hatemile/util/html/htmldomtextnode.py
hatemile/util/html/bs/__init__.py
hatemile/util/html/bs/bshtmldomnode.py
hatemile/util/html/bs/bshtmldomparser.py
hatemile-2.0.1.dist-info/METADATA
hatemile-2.0.1.dist-info/RECORD
hatemile-2.0.1.dist-info/WHEEL
hatemile-2.0.1.dist-info/top_level.txt
js/common.js
js/eventlistener.js
js/include.js
js/scriptlist_validation_fields.js
js/validation.js
