Metadata-Version: 2.1
Name: hatemile
Version: 2.0.1
Summary: HaTeMiLe is a library that can convert a HTML code in a HTML code more accessible.
Home-page: https://github.com/hatemile/hatemile-for-python
Author: Carlson Santana Cruz
License: Apache2
Platform: UNKNOWN
Classifier: Development Status :: 5 - Production/Stable
Classifier: Intended Audience :: Developers
Classifier: License :: OSI Approved :: Apache Software License
Classifier: Programming Language :: Python :: 3
Classifier: Natural Language :: English
Classifier: Topic :: Software Development :: Libraries
Provides-Extra: dev
Requires-Dist: beautifulsoup4 (>=4.6.0)
Requires-Dist: certifi (>=2018.4.16)
Requires-Dist: chardet (>=3.0.4)
Requires-Dist: idna (>=2.6)
Requires-Dist: requests (>=2.18.4)
Requires-Dist: tinycss (>=0.4)
Requires-Dist: urllib3 (>=1.22)
Provides-Extra: dev
Requires-Dist: alabaster (>=0.7.10); extra == 'dev'
Requires-Dist: astroid (>=1.6.5); extra == 'dev'
Requires-Dist: atomicwrites (>=1.1.5); extra == 'dev'
Requires-Dist: attrs (>=18.1.0); extra == 'dev'
Requires-Dist: Babel (>=2.6.0); extra == 'dev'
Requires-Dist: docutils (>=0.14); extra == 'dev'
Requires-Dist: imagesize (>=1.0.0); extra == 'dev'
Requires-Dist: isort (>=4.3.4); extra == 'dev'
Requires-Dist: Jinja2 (>=2.10); extra == 'dev'
Requires-Dist: lazy-object-proxy (>=1.3.1); extra == 'dev'
Requires-Dist: MarkupSafe (>=1.0); extra == 'dev'
Requires-Dist: mccabe (>=0.6.1); extra == 'dev'
Requires-Dist: more-itertools (>=4.2.0); extra == 'dev'
Requires-Dist: packaging (>=17.1); extra == 'dev'
Requires-Dist: pluggy (>=0.6.0); extra == 'dev'
Requires-Dist: py (>=1.5.4); extra == 'dev'
Requires-Dist: pycodestyle (>=2.4.0); extra == 'dev'
Requires-Dist: Pygments (>=2.2.0); extra == 'dev'
Requires-Dist: pylint (>=1.9.2); extra == 'dev'
Requires-Dist: pyparsing (>=2.2.0); extra == 'dev'
Requires-Dist: pytest (>=3.6.2); extra == 'dev'
Requires-Dist: pytz (>=2018.4); extra == 'dev'
Requires-Dist: six (>=1.11.0); extra == 'dev'
Requires-Dist: snowballstemmer (>=1.2.1); extra == 'dev'
Requires-Dist: Sphinx (>=1.7.5); extra == 'dev'
Requires-Dist: sphinxcontrib-websupport (>=1.1.0); extra == 'dev'
Requires-Dist: wrapt (>=1.10.11); extra == 'dev'
